mipx/__init__.py
mipx/_version.py
mipx/commonsolver.py
mipx/constants.py
mipx/cplexcpsolver.py
mipx/cplexmpsolver.py
mipx/cpmodel.py
mipx/cpsolver.py
mipx/func.py
mipx/gurobisolver.py
mipx/interface_.py
mipx/knapsack.py
mipx/lineExpr.py
mipx/maxflow.py
mipx/mincost.py
mipx/model.py
mipx/tupledict.py
mipx/tuplelist.py
mipx/types.py
mipx/utilx.py
mipx/variable.py
mipx/variable_cplex.py
mipx/vrp/__init__.py
mipx/vrp/extra.py
mipx/vrp/vrp.py
mipx-0.7.9.dist-info/LICENSE
mipx-0.7.9.dist-info/METADATA
mipx-0.7.9.dist-info/WHEEL
mipx-0.7.9.dist-info/top_level.txt
mipx-0.7.9.dist-info/RECORD
