Metadata-Version: 2.1
Name: mipx
Version: 0.7.9
Home-page: 
Author: ly
Author-email: 2662017230@qq.com
Classifier: Programming Language :: Python :: 3
Classifier: Operating System :: OS Independent
Classifier: License :: OSI Approved :: Apache Software License
Requires-Python: >=3.8
License-File: LICENSE
Requires-Dist: ortools<=9.14.6206,>=9.9.3963
Provides-Extra: docplex
Requires-Dist: docplex<3.0.0,>=2.25.0; extra == "docplex"
